json_query-0.0.2.dist-info/DESCRIPTION.rst
json_query-0.0.2.dist-info/METADATA
json_query-0.0.2.dist-info/RECORD
json_query-0.0.2.dist-info/WHEEL
json_query-0.0.2.dist-info/entry_points.txt
json_query-0.0.2.dist-info/metadata.json
json_query-0.0.2.dist-info/top_level.txt
jsonquery/__init__.py
jsonquery/jsonquery.py
jsonquery/tests/__init__.py
jsonquery/tests/test_jsonquery.py
